{"queries":[
{"number": "TREC_Entity-15", "text": "#pfsdm(Universities that are members of the SEC conference for football)"},
{"number": "INEX_XER-144", "text": "#pfsdm(chess world champions)"},
{"number": "TREC_Entity-7", "text": "#pfsdm(Airlines that currently use Boeing 747 planes)"},
{"number": "SemSearch_LS-46", "text": "#pfsdm(where the British monarch is also head of state)"},
{"number": "SemSearch_LS-10", "text": "#pfsdm(did nicole kidman have any siblings)"},
{"number": "INEX_XER-126", "text": "#pfsdm(toy train manufacturers that are still in business)"},
{"number": "INEX_XER-123", "text": "#pfsdm(FIFA world cup national team winners since 1974)"},
{"number": "INEX_XER-73", "text": "#pfsdm(magazines about indie music)"},
{"number": "TREC_Entity-4", "text": "#pfsdm(Professional sports teams in Philadelphia)"},
{"number": "TREC_Entity-19", "text": "#pfsdm(Companies that John Hennessey serves on the board of)"},
{"number": "INEX_XER-113", "text": "#pfsdm(Formula 1 drivers that won the Monaco Grand Prix)"},
{"number": "TREC_Entity-17", "text": "#pfsdm(Chefs with a show on the Food Network)"},
{"number": "INEX_XER-128", "text": "#pfsdm(Bond girls)"},
{"number": "INEX_XER-100", "text": "#pfsdm(Operating systems to which Steve Jobs related)"},
{"number": "TREC_Entity-5", "text": "#pfsdm(Products of Medimmune Inc)"},
{"number": "INEX_XER-108", "text": "#pfsdm(State capitals of the United States of America)"},
{"number": "INEX_XER-97", "text": "#pfsdm(Compilers that can compile both C and C++)"},
{"number": "SemSearch_LS-14", "text": "#pfsdm(gods who dwelt on Mount Olympus)"},
{"number": "SemSearch_LS-43", "text": "#pfsdm(what books did paul of tarsus write)"},
{"number": "INEX_XER-96", "text": "#pfsdm(Pure object oriented programing languages)"},
{"number": "SemSearch_LS-29", "text": "#pfsdm(nations where Portuguese is an official language)"},
{"number": "SemSearch_LS-4", "text": "#pfsdm(Axis powers of World War II)"},
{"number": "SemSearch_LS-35", "text": "#pfsdm(republics of the former Yugoslavia)"},
]}
