{ "name" : "default-best" , "score" : "0.11597477843273818" , "uni-attributes-/nnp" : 0.17761826454859034 , "uni-attributes-fieldlikelihood" : 0.3179263071322283 , "uni-categories-/nnp" : 0.0 , "uni-categories-fieldlikelihood" : 0.31109071220190454 , "uni-names-/nnp" : 0.07305564143935725 , "uni-names-fieldlikelihood" : 0.0 , "uni-outgoingentitynames-/nnp" : 0.0 , "uni-outgoingentitynames-fieldlikelihood" : 0.0 , "uni-similarentitynames-/nnp" : 0.0 , "uni-similarentitynames-fieldlikelihood" : 0.12030907467791965 }
